src/cli.py
src/config.py
src/gradio_app.py
src/main.py
src/qa_system.py
src/tools_registry.py
beaglemind_cli-1.0.5.dist-info/METADATA
beaglemind_cli-1.0.5.dist-info/WHEEL
beaglemind_cli-1.0.5.dist-info/entry_points.txt
beaglemind_cli-1.0.5.dist-info/top_level.txt
beaglemind_cli-1.0.5.dist-info/RECORD
