Metadata-Version: 2.4
Name: beaglemind-cli
Version: 1.0.5
Summary: Intelligent documentation assistant CLI for Beagleboard projects
Author-email: Fayez Zouari <fayez.zouari@insat.ucar.tn>
License: MIT
Project-URL: Homepage, https://github.com/beagleboard-gsoc/BeagleMind-RAG-PoC
Project-URL: Repository, https://github.com/beagleboard-gsoc/BeagleMind-RAG-PoC
Project-URL: Bug Tracker, https://github.com/beagleboard-gsoc/BeagleMind-RAG-PoC/issues
Keywords: cli,documentation,AI,RAG,beagleboard
Classifier: Development Status :: 4 - Beta
Classifier: Intended Audience :: Developers
Classifier: License :: OSI Approved :: MIT License
Classifier: Programming Language :: Python :: 3
Classifier: Programming Language :: Python :: 3.8
Classifier: Programming Language :: Python :: 3.9
Classifier: Programming Language :: Python :: 3.10
Classifier: Programming Language :: Python :: 3.11
Classifier: Topic :: Software Development :: Documentation
Classifier: Topic :: Scientific/Engineering :: Artificial Intelligence
Requires-Python: >=3.8
Requires-Dist: click>=8.0.0
Requires-Dist: rich>=12.0.0
Requires-Dist: gradio>=4.0.0
Requires-Dist: python-dotenv>=1.0.0
Requires-Dist: numpy>=1.21.0
Requires-Dist: requests>=2.25.0
Requires-Dist: openai
Provides-Extra: dev
Requires-Dist: pytest>=7.0.0; extra == "dev"
Requires-Dist: black>=22.0.0; extra == "dev"
Requires-Dist: flake8>=4.0.0; extra == "dev"
Requires-Dist: mypy>=0.910; extra == "dev"
